myx/__init__.py
myx/client.py
myx-0.1.1.dist-info/LICENSE
myx-0.1.1.dist-info/METADATA
myx-0.1.1.dist-info/WHEEL
myx-0.1.1.dist-info/top_level.txt
myx-0.1.1.dist-info/RECORD
