Metadata-Version: 2.1
Name: myx
Version: 0.1.1
Summary: Wrapper around MYX's One3D platform API
Home-page: https://gitlab.myxrobotics.com/stanislav.nikolov/myx-api-wrapper-python
Author: Stanislav Ch. Nikolov
Author-email: stanislav.nikolov@myxrobotics.com
Project-URL: Documentation, https://docs.myxrobotics.com
Classifier: Programming Language :: Python :: 3
Classifier: License :: OSI Approved :: MIT License
Classifier: Operating System :: OS Independent
Requires-Python: >=3.6
License-File: LICENSE
Requires-Dist: requests
